{
    "data": {
        "menu": [
            {
                "id":"0",
                "name":"세트 메뉴",
                "event":"true"
            },
            {
                "id":"1",
                "name":"단품 메뉴",
                "event":"false"
            },
            {
                "id":"2",
                "name":"사이드 메뉴",
                "event":"false"
            },
            {
                "id":"3",
                "name":"디저트 메뉴",
                "event":"true"
            },
            {
                "id":"4",
                "name":"음료",
                "event":"false"
            },
            {
                "id":"5",
                "name":"치킨",
                "event":"false"
            }
        ],
        "set":[
            {
                "id":0,
                "name": "슈슈 버거 세트"
            },
            {
                "id":1,
                "name": "슈슈 버거 라지 세트"
            },
            {
                "id":2,
                "name": "슈비 버거 세트"
            },
            {
                "id":3,
                "name": "슈비 버거 라지 세트"
            },
            {
                "id":4,
                "name": "슈가 버거 세트"
            },
            {
                "id":5,
                "name": "슈가 버거 라지 세트"
            },
            {
                "id":6,
                "name": "슈나 버거 세트"
            },
            {
                "id":7,
                "name": "슈나 버거 라지 세트"
            },
            {
                "id":8,
                "name": "슈다 버거 세트"
            },
            {
                "id":9,
                "name": "슈다 버거 라지 세트"
            },
            {
                "id":10,
                "name": "슈라 버거 세트"
            },
            {
                "id":11,
                "name": "슈라 버거 라지 세트"
            },
            {
                "id":12,
                "name": "슈마 버거 세트"
            },
            {
                "id":13,
                "name": "슈바 버거 세트"
            }
        ]
    }    
}